{
  "recentFiles": [
    {
      "basename": "2022.12.16.卷纸",
      "path": "2022.12.16.卷纸.md"
    },
    {
      "basename": "2022.06.16.茶饮",
      "path": "2022.06.16.茶饮.md"
    },
    {
      "basename": "2022.06.16.菊花茶",
      "path": "2022.06.16.菊花茶.md"
    },
    {
      "basename": "2023.06.01.烧烤酱",
      "path": "2023.06.01.烧烤酱.md"
    },
    {
      "basename": "2023.06.01.牛肉酱",
      "path": "2023.06.01.牛肉酱.md"
    },
    {
      "basename": "2023.06.01.蘑菇酱",
      "path": "2023.06.01.蘑菇酱.md"
    },
    {
      "basename": "2023.06.01.辣酱",
      "path": "2023.06.01.辣酱.md"
    },
    {
      "basename": "2023.06.01.酱汁",
      "path": "2023.06.01.酱汁.md"
    },
    {
      "basename": "2023.06.01.酱料",
      "path": "2023.06.01.酱料.md"
    },
    {
      "basename": "2023.06.01.干碟",
      "path": "2023.06.01.干碟.md"
    },
    {
      "basename": "2023.06.01.拌饭酱",
      "path": "2023.06.01.拌饭酱.md"
    },
    {
      "basename": "2023.05.31.新奥尔良腌料",
      "path": "2023.05.31.新奥尔良腌料.md"
    },
    {
      "basename": "2023.05.31.洗衣液",
      "path": "2023.05.31.洗衣液.md"
    },
    {
      "basename": "2023.05.31.洁厕剂",
      "path": "2023.05.31.洁厕剂.md"
    },
    {
      "basename": "2023.05.30.衣领净",
      "path": "2023.05.30.衣领净.md"
    },
    {
      "basename": "2023.05.30.插排",
      "path": "2023.05.30.插排.md"
    },
    {
      "basename": "2023.05.30.路由器",
      "path": "2023.05.30.路由器.md"
    },
    {
      "basename": "2022.07.14.去渍",
      "path": "2022.07.14.去渍.md"
    },
    {
      "basename": "2023.04.18.电纸书",
      "path": "2023.04.18.电纸书.md"
    },
    {
      "basename": "2022.12.14.新冠药品清单",
      "path": "2022.12.14.新冠药品清单.md"
    },
    {
      "basename": "2022.12.16.纸抽",
      "path": "2022.12.16.纸抽.md"
    },
    {
      "basename": "2022.12.14.空气净化器",
      "path": "2022.12.14.空气净化器.md"
    },
    {
      "basename": "2022.07.14.棉柔巾",
      "path": "2022.07.14.棉柔巾.md"
    },
    {
      "basename": "2022.07.06.湿巾",
      "path": "2022.07.06.湿巾.md"
    },
    {
      "basename": "2022.11.16.鞋",
      "path": "2022.11.16.鞋.md"
    },
    {
      "basename": "2022.10.25.去黑头",
      "path": "2022.10.25.去黑头.md"
    },
    {
      "basename": "2022.07.31.蚧壳虫药",
      "path": "2022.07.31.蚧壳虫药.md"
    },
    {
      "basename": "2022.07.14.卫生湿巾",
      "path": "2022.07.14.卫生湿巾.md"
    },
    {
      "basename": "2022.06.22.杂粮",
      "path": "2022.06.22.杂粮.md"
    },
    {
      "basename": "2022.06.22.乳制品",
      "path": "2022.06.22.乳制品.md"
    },
    {
      "basename": "2022.06.22.饼干",
      "path": "2022.06.22.饼干.md"
    },
    {
      "basename": "2022.06.18.甜品",
      "path": "2022.06.18.甜品.md"
    },
    {
      "basename": "2022.06.18.干果",
      "path": "2022.06.18.干果.md"
    },
    {
      "basename": "2022.06.17.饮料",
      "path": "2022.06.17.饮料.md"
    },
    {
      "basename": "2022.06.17.水果茶",
      "path": "2022.06.17.水果茶.md"
    },
    {
      "basename": "2022.06.17.乳饮",
      "path": "2022.06.17.乳饮.md"
    },
    {
      "basename": "2022.06.17.可可粉",
      "path": "2022.06.17.可可粉.md"
    },
    {
      "basename": "2022.06.17.果汁",
      "path": "2022.06.17.果汁.md"
    },
    {
      "basename": "2022.06.17.果饮",
      "path": "2022.06.17.果饮.md"
    },
    {
      "basename": "2022.06.17.水果茶",
      "path": "_posts/2022.06.17.水果茶.md"
    },
    {
      "basename": "index",
      "path": "about/index.md"
    },
    {
      "basename": "index",
      "path": "links/index.md"
    },
    {
      "basename": "2023.06.01.拌饭酱",
      "path": "_posts/2023.06.01.拌饭酱.md"
    },
    {
      "basename": "2022.06.17.果汁",
      "path": "_posts/2022.06.17.果汁.md"
    },
    {
      "basename": "2023.06.01.烧烤酱",
      "path": "_posts/2023.06.01.烧烤酱.md"
    },
    {
      "basename": "2023.06.01.牛肉酱",
      "path": "_posts/2023.06.01.牛肉酱.md"
    },
    {
      "basename": "2023.06.01.蘑菇酱",
      "path": "_posts/2023.06.01.蘑菇酱.md"
    },
    {
      "basename": "2023.06.01.辣酱",
      "path": "_posts/2023.06.01.辣酱.md"
    },
    {
      "basename": "2023.06.01.酱汁",
      "path": "_posts/2023.06.01.酱汁.md"
    },
    {
      "basename": "2023.06.01.酱料",
      "path": "_posts/2023.06.01.酱料.md"
    }
  ],
  "omittedPaths": [],
  "maxLength": null,
  "openType": "tab"
}